pysymbol_llm/__init__.py
pysymbol_llm/_modidx.py
pysymbol_llm/core.py
pysymbol_llm-0.0.5.dist-info/LICENSE
pysymbol_llm-0.0.5.dist-info/METADATA
pysymbol_llm-0.0.5.dist-info/WHEEL
pysymbol_llm-0.0.5.dist-info/entry_points.txt
pysymbol_llm-0.0.5.dist-info/top_level.txt
pysymbol_llm-0.0.5.dist-info/RECORD
